quapp_common/__init__.py
quapp_common/async_tasks/__init__.py
quapp_common/async_tasks/async_invocation_task.py
quapp_common/async_tasks/async_task.py
quapp_common/async_tasks/export_circuit_task.py
quapp_common/async_tasks/post_processing_task.py
quapp_common/component/__init__.py
quapp_common/component/backend/__init__.py
quapp_common/component/backend/invocation.py
quapp_common/component/backend/job_fetcher.py
quapp_common/component/backend/job_fetching.py
quapp_common/component/backend/job_manager.py
quapp_common/component/callback/__init__.py
quapp_common/component/callback/update_job_metadata.py
quapp_common/component/device/__init__.py
quapp_common/component/device/device_selection.py
quapp_common/config/__init__.py
quapp_common/config/logging_config.py
quapp_common/config/thread_config.py
quapp_common/data/__init__.py
quapp_common/data/async_task/__init__.py
quapp_common/data/async_task/circuit_export/__init__.py
quapp_common/data/async_task/circuit_export/backend_holder.py
quapp_common/data/async_task/circuit_export/circuit_holder.py
quapp_common/data/backend/__init__.py
quapp_common/data/backend/backend_information.py
quapp_common/data/callback/__init__.py
quapp_common/data/callback/callback_url.py
quapp_common/data/device/__init__.py
quapp_common/data/device/circuit_running_option.py
quapp_common/data/promise/__init__.py
quapp_common/data/promise/post_processing_promise.py
quapp_common/data/promise/promise.py
quapp_common/data/request/__init__.py
quapp_common/data/request/invocation_request.py
quapp_common/data/request/job_fetching_request.py
quapp_common/data/request/request.py
quapp_common/data/response/__init__.py
quapp_common/data/response/authentication.py
quapp_common/data/response/custom_header.py
quapp_common/data/response/job_response.py
quapp_common/enum/__init__.py
quapp_common/enum/base_enum.py
quapp_common/enum/http_header.py
quapp_common/enum/invocation_step.py
quapp_common/enum/media_type.py
quapp_common/enum/processing_unit.py
quapp_common-0.0.11.dev9.dist-info/licenses/LICENSE
quapp_common-0.0.11.dev9.dist-info/METADATA
quapp_common-0.0.11.dev9.dist-info/WHEEL
quapp_common-0.0.11.dev9.dist-info/top_level.txt
quapp_common-0.0.11.dev9.dist-info/RECORD
